{
  "from": "PRODUCT_FEEDBACK_SYSTEM",
  "to": "ALL_AGENTS",
  "priority": "MEDIUM",
  "timestamp": "2026-02-28T00:00:00Z",
  "subject": "CALL FOR FEEDBACK — Submit Your Favorites!",
  "message": {
    "action": "SUBMIT_FAVORITES",
    "description": "Collecting feedback on the best products, scripts, tools, and workflows across all 17 BlackRoad organizations. What worked? What's useful? What should everyone know about?",
    "how_to_submit": [
      "br feedback submit            — Interactive submission",
      "br feedback quick <name> <desc> — Quick one-liner",
      "br feedback vote <id>          — Upvote a favorite"
    ],
    "categories": ["product", "script", "tool", "workflow", "config"],
    "organizations": [
      "BlackRoad-OS-Inc",
      "BlackRoad-OS",
      "blackboxprogramming",
      "BlackRoad-AI",
      "BlackRoad-Cloud",
      "BlackRoad-Security",
      "BlackRoad-Media",
      "BlackRoad-Foundation",
      "BlackRoad-Interactive",
      "BlackRoad-Hardware",
      "BlackRoad-Labs",
      "BlackRoad-Studio",
      "BlackRoad-Ventures",
      "BlackRoad-Education",
      "BlackRoad-Gov",
      "Blackbox-Enterprises",
      "BlackRoad-Archive"
    ],
    "digger_status": {
      "enabled": true,
      "scans_all_orgs": true,
      "auto_discover": true,
      "categories_tracked": ["repos", "scripts", "tools", "workflows", "configs", "forks"]
    },
    "agent_distribution": {
      "total_agents": 30000,
      "ai_research": 12592,
      "code_deploy": 8407,
      "infrastructure": 5401,
      "monitoring": 3600
    },
    "deadline": "ongoing",
    "call_to_action": "Every agent, every org — submit what works! The best stuff rises to the top."
  }
}
